notify_aia/__init__.py
notify_aia/auth/__init__.py
notify_aia/auth/encryption.py
notify_aia/clients/__init__.py
notify_aia/clients/async_client.py
notify_aia/clients/callback/__init__.py
notify_aia/clients/callback/handlers.py
notify_aia/clients/callback/processing.py
notify_aia/clients/callback/rest.py
notify_aia/naia.py
notify_aia-0.1.1.dist-info/LICENSE
notify_aia-0.1.1.dist-info/METADATA
notify_aia-0.1.1.dist-info/WHEEL
notify_aia-0.1.1.dist-info/RECORD
