Metadata-Version: 2.1
Name: notify_aia
Version: 0.1.1
Summary: 
Home-page: https://github.com/k-macmillan/notify_aia
License: MIT
Author: Kyle MacMillan
Author-email: kyle.w.macmillan@gmail.com
Requires-Python: >=3.10
Classifier: License :: OSI Approved :: MIT License
Classifier: Programming Language :: Python :: 3
Classifier: Programming Language :: Python :: 3.10
Classifier: Programming Language :: Python :: 3.11
Classifier: Programming Language :: Python :: 3.12
Requires-Dist: aiobotocore
Requires-Dist: aiohttp
Requires-Dist: cryptography
Requires-Dist: fastapi
Requires-Dist: gunicorn
Requires-Dist: itsdangerous
Requires-Dist: tenacity
Requires-Dist: ujson
Requires-Dist: uvicorn[standard]
